tusfastapiserver/__init__.py
tusfastapiserver/config.py
tusfastapiserver/exceptions.py
tusfastapiserver/metadata/__init__.py
tusfastapiserver/metadata/base.py
tusfastapiserver/metadata/local.py
tusfastapiserver/routers/__init__.py
tusfastapiserver/routers/base_router.py
tusfastapiserver/routers/delete_router.py
tusfastapiserver/routers/head_router.py
tusfastapiserver/routers/options_router.py
tusfastapiserver/routers/patch_router.py
tusfastapiserver/routers/post_router.py
tusfastapiserver/schemas.py
tusfastapiserver/storages/__init__.py
tusfastapiserver/storages/base.py
tusfastapiserver/storages/local.py
tusfastapiserver/utils/__init__.py
tusfastapiserver/utils/metadata.py
tusfastapiserver-0.1.0.dist-info/METADATA
tusfastapiserver-0.1.0.dist-info/WHEEL
tusfastapiserver-0.1.0.dist-info/RECORD
